pydbtcloud/__init__.py
pydbtcloud/client.py
pydbtcloud-0.0.3.dist-info/LICENSE
pydbtcloud-0.0.3.dist-info/METADATA
pydbtcloud-0.0.3.dist-info/WHEEL
pydbtcloud-0.0.3.dist-info/top_level.txt
pydbtcloud-0.0.3.dist-info/RECORD
