Metadata-Version: 2.1
Name: pydbtcloud
Version: 0.0.3
Summary: Python SDK for dbt Cloud.
Home-page: https://github.com/dwallace0723/py-dbt-cloud
Author: David Wallace
Author-email: dwallace0723@gmail.com
License: MIT
Keywords: dbt
Platform: UNKNOWN
Classifier: Intended Audience :: Developers
Classifier: License :: OSI Approved :: MIT License
Classifier: Programming Language :: Python
Classifier: Programming Language :: Python :: 3
Classifier: Programming Language :: Python :: 3.7
Requires-Python: >=3.7
Requires-Dist: requests (>=2.22.0)
